torchflare/__init__.py
torchflare/callbacks/__init__.py
torchflare/callbacks/callback.py
torchflare/callbacks/callback_decorators.py
torchflare/callbacks/comet_logger.py
torchflare/callbacks/criterion_callback.py
torchflare/callbacks/early_stopping.py
torchflare/callbacks/extra_utils.py
torchflare/callbacks/load_checkpoint.py
torchflare/callbacks/lr_schedulers.py
torchflare/callbacks/message_notifiers.py
torchflare/callbacks/metric_utils.py
torchflare/callbacks/model_checkpoint.py
torchflare/callbacks/model_history.py
torchflare/callbacks/neptune_logger.py
torchflare/callbacks/progress_bar.py
torchflare/callbacks/states.py
torchflare/callbacks/tensorboard_logger.py
torchflare/callbacks/wandb_logger.py
torchflare/core/__init__.py
torchflare/core/state.py
torchflare/criterion/__init__.py
torchflare/criterion/cross_entropy.py
torchflare/criterion/focal_loss.py
torchflare/criterion/triplet_loss.py
torchflare/criterion/utils.py
torchflare/datasets/__init__.py
torchflare/datasets/core_utils.py
torchflare/datasets/data_core.py
torchflare/datasets/image_data.py
torchflare/datasets/image_segmentation.py
torchflare/datasets/tabular_data.py
torchflare/datasets/text_data.py
torchflare/experiments/__init__.py
torchflare/experiments/backends.py
torchflare/experiments/base_backend.py
torchflare/experiments/commons.py
torchflare/experiments/config.py
torchflare/experiments/criterion_utilities.py
torchflare/experiments/experiment.py
torchflare/experiments/optim_utilities.py
torchflare/experiments/simple_utils.py
torchflare/modules/__init__.py
torchflare/modules/airface.py
torchflare/modules/am_softmax.py
torchflare/modules/arcface.py
torchflare/modules/cosface.py
torchflare/modules/se_modules.py
torchflare/serving/__init__.py
torchflare/serving/api_type.py
torchflare/serving/gradio_app.py
torchflare/utils/__init__.py
torchflare/utils/average_meter.py
torchflare/utils/imports_check.py
torchflare/utils/seeder.py
torchflare-0.2.4.dist-info/LICENSE
torchflare-0.2.4.dist-info/METADATA
torchflare-0.2.4.dist-info/WHEEL
torchflare-0.2.4.dist-info/top_level.txt
torchflare-0.2.4.dist-info/RECORD
