Metadata-Version: 2.1
Name: torchflare
Version: 0.2.4
Summary: TorchFlare is a simple, beginner-friendly, and easy-to-use PyTorch Framework train your models effortlessly.
Home-page: https://github.com/Atharva-Phatak/torchflare
Author: Atharva Phatak
Author-email: athp456@gmail.com
License: Apache License 2.0
Download-URL: https://github.com/Atharva-Phatak/torchflare
Project-URL: Bug Tracker, https://github.com/Atharva-Phatak/torchflare/issues
Project-URL: Documentation, https://atharva-phatak.github.io/torchflare/
Project-URL: Source Code, https://github.com/Atharva-Phatak/torchflare
Keywords: Deep Learning,Computer Vision,Natural Language Processing,PyTorch
Platform: UNKNOWN
Classifier: Environment :: Console
Classifier: Natural Language :: English
Classifier: Development Status :: 3 - Alpha
Classifier: Intended Audience :: Developers
Classifier: Topic :: Scientific/Engineering :: Artificial Intelligence
Classifier: Topic :: Scientific/Engineering :: Image Recognition
Classifier: Topic :: Scientific/Engineering :: Information Analysis
Classifier: License :: OSI Approved :: Apache Software License
Classifier: Operating System :: OS Independent
Classifier: Programming Language :: Python :: 3
Classifier: Programming Language :: Python :: 3.6
Classifier: Programming Language :: Python :: 3.7
Classifier: Programming Language :: Python :: 3.8
Requires-Python: >=3.7.0
License-File: LICENSE
Requires-Dist: numpy (==1.20.3)
Requires-Dist: pandas (==1.2.5)
Requires-Dist: torch (==1.9.0)
Requires-Dist: torchvision (==0.10.0)
Requires-Dist: albumentations (==1.0.0)
Requires-Dist: torchmetrics (==0.5.0)
Requires-Dist: gradio (==2.2.13)
